{
  "100": [
    {
      "price": 100,
      "orderId": 115,
      "type": "bid",
      "size": 99
    }
  ],
  "10000": [
    {
      "price": 10000,
      "orderId": 129,
      "type": "bid",
      "size": 10000
    }
  ],
  "10001": [
    {
      "price": 10001,
      "orderId": 133,
      "type": "bid",
      "size": 100
    }
  ],
  "49000": [
    {
      "price": 49000,
      "orderId": 108,
      "type": "bid",
      "size": 15000
    }
  ],
  "49999": [
    {
      "price": 49999,
      "orderId": 107,
      "type": "bid",
      "size": 5000
    }
  ],
  "50000": [
    {
      "price": 50000,
      "orderId": 119,
      "type": "bid",
      "size": 49
    }
  ],
  "100000": [
    {
      "price": 100000,
      "orderId": 126,
      "type": "bid",
      "size": 1
    }
  ]
}